<DOMSymbolItem xmlns="http://ns.adobe.com/xfl/2008/" xmlns:xsi="http://www.w3.org/2001/XMLSchema-instance" name="Symbol 307" lastModified="1701854705">
     <timeline>
          <DOMTimeline name="Symbol 307">
               <layers>
                    <DOMLayer name="Layer 1" color="#a2fa27">
                         <frames>
                              <DOMFrame index="0" duration="2" keyMode="9728">
                                   <elements>
                                        <DOMShape isFloating="true">
                                             <fills>
                                                  <FillStyle index="1">
                                                       <SolidColor color="#ffffff"/>
                                                  </FillStyle>
                                             </fills>
                                             <strokes/>
                                             <edges>
                                                  <Edge fillStyle0="0" fillStyle1="1" strokeStyle="0" edges="! -252 90[ -227 90 -213 103"/>
                                                  <Edge fillStyle0="0" fillStyle1="1" strokeStyle="0" edges="! -203 118[ -203 128 -220 134"/>
                                                  <Edge fillStyle0="0" fillStyle1="1" strokeStyle="0" edges="! -213 103[ -203 112 -203 118"/>
                                                  <Edge fillStyle0="0" fillStyle1="1" strokeStyle="0" edges="! -220 134| -254 139| -291 130| -302 115[ -302 106 -290 99| -281 95| -273 92| -268 90| -252 90"/>
                                                  <Edge fillStyle0="0" fillStyle1="1" strokeStyle="0" edges="! -223 193[ -232 193 -238 186| -243 176[ -243 163 -222 165[ -202 167 -202 177| -208 188| -223 193"/>
                                             </edges>
                                        </DOMShape>
                                   </elements>
                              </DOMFrame>
                         </frames>
                    </DOMLayer>
                    <DOMLayer name="Layer 2" color="#25b8e4">
                         <frames>
                              <DOMFrame index="0" duration="2" keyMode="9728">
                                   <elements>
                                        <DOMSymbolInstance libraryItemName="Symbol 305" name="_col2" centerPoint3DX="13.15" centerPoint3DY="17.3">
                                             <matrix>
                                                  <Matrix tx="-3.45" ty="1.65"/>
                                             </matrix>
                                             <transformationPoint>
                                                  <Point/>
                                             </transformationPoint>
                                        </DOMSymbolInstance>
                                   </elements>
                              </DOMFrame>
                         </frames>
                    </DOMLayer>
                    <DOMLayer name="Layer 3" color="#10e1b6" current="true" isSelected="true">
                         <frames>
                              <DOMFrame index="0" duration="2" keyMode="9728">
                                   <elements>
                                        <DOMSymbolInstance libraryItemName="Symbol 303" name="_col3" centerPoint3DX="18.75" centerPoint3DY="16.5">
                                             <matrix>
                                                  <Matrix tx="0.3" ty="-1.8"/>
                                             </matrix>
                                             <transformationPoint>
                                                  <Point/>
                                             </transformationPoint>
                                        </DOMSymbolInstance>
                                   </elements>
                              </DOMFrame>
                         </frames>
                    </DOMLayer>
               </layers>
          </DOMTimeline>
     </timeline>
</DOMSymbolItem>
