<DOMSymbolItem xmlns="http://ns.adobe.com/xfl/2008/" xmlns:xsi="http://www.w3.org/2001/XMLSchema-instance" name="Symbol 575" lastModified="1701854705">
     <timeline>
          <DOMTimeline name="Symbol 575">
               <layers>
                    <DOMLayer name="Layer 1" color="#a8b5e9" current="true" isSelected="true">
                         <frames>
                              <DOMFrame index="0" keyMode="9728">
                                   <elements>
                                        <DOMShape isFloating="true">
                                             <fills>
                                                  <FillStyle index="1">
                                                       <SolidColor color="#d6baba" alpha="1.0"/>
                                                  </FillStyle>
                                                  <FillStyle index="2">
                                                       <SolidColor color="#ffffff" alpha="1.0"/>
                                                  </FillStyle>
                                             </fills>
                                             <strokes>
                                                  <StrokeStyle index="1">
                                                       <SolidStroke scaleMode="normal" weight="0.05">
                                                            <fill>
                                                                 <SolidColor color="#000000" alpha="0.3019608"/>
                                                            </fill>
                                                       </SolidStroke>
                                                  </StrokeStyle>
                                             </strokes>
                                             <edges>
                                                  <Edge fillStyle0="1" fillStyle1="0" strokeStyle="1" edges="! 359 85| 305 30| 305 18| 302 6| 293 12[ 259 33 255 67[ 309 98 303 141[ 301 161 281 178| 259 195[ 346 166 366 106[ 370 94 359 85"/>
                                                  <Edge fillStyle0="2" fillStyle1="0" strokeStyle="1" edges="! 66 175| 50 166| 35 152| 32 143| 32 133| 92 95[ 118 77 117 51| 77 7[ 53 46 9 80| -30 113[ -20 152 34 168| 46 172| 49 173| 68 177"/>
                                                  <Edge fillStyle0="2" fillStyle1="0" strokeStyle="0" edges="! 68 177| 68 176| 66 175"/>
                                             </edges>
                                        </DOMShape>
                                   </elements>
                              </DOMFrame>
                         </frames>
                    </DOMLayer>
               </layers>
          </DOMTimeline>
     </timeline>
</DOMSymbolItem>
