<DOMSymbolItem xmlns="http://ns.adobe.com/xfl/2008/" xmlns:xsi="http://www.w3.org/2001/XMLSchema-instance" name="Symbol 645" lastModified="1701854705">
     <timeline>
          <DOMTimeline name="Symbol 645">
               <layers>
                    <DOMLayer name="Layer 1" color="#bcc3ac" current="true" isSelected="true">
                         <frames>
                              <DOMFrame index="0" keyMode="9728">
                                   <elements>
                                        <DOMShape isFloating="true">
                                             <fills>
                                                  <FillStyle index="1">
                                                       <SolidColor color="#ffffff" alpha="1.0"/>
                                                  </FillStyle>
                                                  <FillStyle index="2">
                                                       <SolidColor color="#d6baba" alpha="1.0"/>
                                                  </FillStyle>
                                             </fills>
                                             <strokes>
                                                  <StrokeStyle index="1">
                                                       <SolidStroke scaleMode="normal" weight="0.05">
                                                            <fill>
                                                                 <SolidColor color="#000000" alpha="0.4"/>
                                                            </fill>
                                                       </SolidStroke>
                                                  </StrokeStyle>
                                             </strokes>
                                             <edges>
                                                  <Edge fillStyle0="0" fillStyle1="1" strokeStyle="1" edges="! -177 -61[ -167 -112 -129 -139| -68 -179| -45 -185| 7 -179| 74 -166| 181 -150[ 120 -97 95 -60[ 70 -23 59 21"/>
                                                  <Edge fillStyle0="0" fillStyle1="2" strokeStyle="1" edges="! 59 21| 58 27| 56 36"/>
                                                  <Edge fillStyle0="0" fillStyle1="2" strokeStyle="1" edges="! 51 90[ 51 131 59 185"/>
                                                  <Edge fillStyle0="0" fillStyle1="2" strokeStyle="1" edges="! 56 36[ 51 62 51 90"/>
                                                  <Edge fillStyle0="0" fillStyle1="0" strokeStyle="1" edges="! 59 185| 60 187| 58 186"/>
                                                  <Edge fillStyle0="0" fillStyle1="2" strokeStyle="1" edges="! 58 186| -73 96[ -105 74 -153 72[ -181 43 -181 12| -181 -28| -180 -41| -177 -61"/>
                                                  <Edge fillStyle0="1" fillStyle1="2" strokeStyle="0" edges="! -177 -61| -150 -64| -76 -60| -56 -51| 19 -5| 59 21"/>
                                                  <Edge fillStyle0="2" fillStyle1="0" strokeStyle="0" edges="! 58 186| 59 185"/>
                                             </edges>
                                        </DOMShape>
                                   </elements>
                              </DOMFrame>
                         </frames>
                    </DOMLayer>
               </layers>
          </DOMTimeline>
     </timeline>
</DOMSymbolItem>
