<DOMSymbolItem xmlns="http://ns.adobe.com/xfl/2008/" xmlns:xsi="http://www.w3.org/2001/XMLSchema-instance" name="Symbol 390" lastModified="1701854705">
     <timeline>
          <DOMTimeline name="Symbol 390">
               <layers>
                    <DOMLayer name="Layer 1" color="#b755be" current="true" isSelected="true">
                         <frames>
                              <DOMFrame index="0" keyMode="9728">
                                   <elements>
                                        <DOMShape isFloating="true">
                                             <fills>
                                                  <FillStyle index="1">
                                                       <SolidColor color="#ffffff" alpha="1.0"/>
                                                  </FillStyle>
                                                  <FillStyle index="2">
                                                       <SolidColor color="#d6baba" alpha="1.0"/>
                                                  </FillStyle>
                                             </fills>
                                             <strokes>
                                                  <StrokeStyle index="1">
                                                       <SolidStroke scaleMode="normal" weight="0.05">
                                                            <fill>
                                                                 <SolidColor color="#000000" alpha="0.3019608"/>
                                                            </fill>
                                                       </SolidStroke>
                                                  </StrokeStyle>
                                             </strokes>
                                             <edges>
                                                  <Edge fillStyle0="0" fillStyle1="1" strokeStyle="1" edges="! 10 134[ -26 193 -54 251[ -110 365 -161 425[ -103 330 -36 7[ -3 -150 29 -246[ -26 -170 -133 -46| -443 311[ -589 495 -706 577[ -758 613 -788 621| -718 511[ -612 332 -584 242| -725 397[ -837 519 -871 549| -788 410[ -716 283 -702 217[ -665 41 -509 -209[ -426 -341 -365 -411[ -431 -440 -463 -498| -494 -620[ -476 -588 -404 -553[ -336 -519 -271 -508[ -121 -555 -24 -574| 205 -596[ 291 -596 416 -544| 419 -543| 454 -527| 455 -527[ 535 -486 556 -451| 574 -499| 597 -550[ 604 -546 628 -494[ 650 -447 667 -445[ 698 -442 774 -408| 835 -379"/>
                                                  <Edge fillStyle0="0" fillStyle1="2" strokeStyle="1" edges="! 835 -379| 855 -367| 800 -363[ 773 -355 755 -341[ 766 -339 781 -319[ 804 -287 836 -210[ 888 -85 860 61[ 831 207 671 342[ 510 476 441 464[ 408 504 386 513| 408 415| 436 276| 399 323| 365 363| 419 180| 441 83| 369 208[ 254 385 81 497"/>
                                                  <Edge fillStyle0="0" fillStyle1="1" strokeStyle="1" edges="! 81 497| -35 561| 16 522| 42 501[ 118 439 138 378[ 156 323 248 -83| 254 -112"/>
                                                  <Edge fillStyle0="0" fillStyle1="2" strokeStyle="0" edges="! 254 -112| 250 -113| 261 -163"/>
                                                  <Edge fillStyle0="0" fillStyle1="2" strokeStyle="1" edges="! 261 -163| 219 -135[ 168 -106 85 15| 10 134"/>
                                                  <Edge fillStyle0="1" fillStyle1="2" strokeStyle="0" edges="! -411 -15| -243 -178[ -136 -270 -10 -331| -6 -327| -214 -168| -408 -13| -411 -15"/>
                                                  <Edge fillStyle0="2" fillStyle1="1" strokeStyle="0" edges="! 261 -163| 272 -230| 272 -315| 261 -315[ 62 36 10 134"/>
                                                  <Edge fillStyle0="1" fillStyle1="0" strokeStyle="1" edges="! 261 -163| 267 -170| 266 -162"/>
                                                  <Edge fillStyle0="1" fillStyle1="2" strokeStyle="1" edges="! 266 -162| 254 -112"/>
                                                  <Edge fillStyle0="2" fillStyle1="0" strokeStyle="0" edges="! 266 -162| 261 -163"/>
                                                  <Edge fillStyle0="2" fillStyle1="1" strokeStyle="0" edges="! 835 -379| 799 -381[ 747 -381 730 -370[ 712 -359 661 -384[ 610 -410 603 -460| 603 -346| 619 -353| 613 -276[ 587 -293 565 -321| 529 -366| 528 -363[ 537 -345 537 -277| 535 -237| 505 -198[ 468 -145 448 -85[ 393 74 285 251[ 175 431 79 493| 81 497"/>
                                                  <Edge fillStyle0="2" fillStyle1="2" strokeStyle="1" edges="! 441 464| 465 433| 512 364"/>
                                                  <Edge fillStyle0="2" fillStyle1="0" strokeStyle="1" edges="! 436 276| 437 268| 437 274| 436 276"/>
                                                  <Edge fillStyle0="0" fillStyle1="1" strokeStyle="1" edges="! -582 240| -582 235| -584 242| -582 240"/>
                                             </edges>
                                        </DOMShape>
                                   </elements>
                              </DOMFrame>
                         </frames>
                    </DOMLayer>
               </layers>
          </DOMTimeline>
     </timeline>
</DOMSymbolItem>
