<DOMSymbolItem xmlns="http://ns.adobe.com/xfl/2008/" xmlns:xsi="http://www.w3.org/2001/XMLSchema-instance" name="Symbol 312" lastModified="1701854705" symbolType="graphic">
     <timeline>
          <DOMTimeline name="Symbol 312" currentFrame="0">
               <layers>
                    <DOMLayer name="Layer 1">
                         <frames>
                              <DOMFrame index="0" motionTweenScale="false" keyMode="8192">
                                   <elements>
                                        <DOMShape isFloating="true">
                                             <fills>
                                                  <FillStyle index="1">
                                                       <SolidColor color="#d1b6b6" alpha="1.0"/>
                                                  </FillStyle>
                                                  <FillStyle index="2">
                                                       <SolidColor color="#ffffff" alpha="1.0"/>
                                                  </FillStyle>
                                             </fills>
                                             <strokes>
                                                  <StrokeStyle index="1">
                                                       <SolidStroke scaleMode="normal" weight="0.05">
                                                            <fill>
                                                                 <SolidColor color="#000000" alpha="0.3019608"/>
                                                            </fill>
                                                       </SolidStroke>
                                                  </StrokeStyle>
                                             </strokes>
                                             <edges>
                                                  <Edge fillStyle0="1" fillStyle1="0" strokeStyle="1" edges="! 329 241| 355 226| 367 218| 379 210| 383 206[ 393 194 388 132"/>
                                                  <Edge fillStyle0="1" fillStyle1="1" strokeStyle="1" edges="! 388 132| 324 173"/>
                                                  <Edge fillStyle0="1" fillStyle1="2" strokeStyle="1" edges="! 324 173| 329 241"/>
                                                  <Edge fillStyle0="0" fillStyle1="2" strokeStyle="1" edges="! 329 241| 319 246[ 294 263 154 378| 81 356| 34 335[ 28 328 27 300[ 26 226 0 53| 1 52"/>
                                                  <Edge fillStyle0="0" fillStyle1="1" strokeStyle="1" edges="! 1 52[ 3 43 42 0| 388 132"/>
                                                  <Edge fillStyle0="0" fillStyle1="2" strokeStyle="1" edges="! 35 182[ 35 240 62 278"/>
                                                  <Edge fillStyle0="0" fillStyle1="2" strokeStyle="1" edges="! 100 308[ 144 308 168 270"/>
                                                  <Edge fillStyle0="0" fillStyle1="2" strokeStyle="1" edges="! 62 278[ 83 308 100 308"/>
                                                  <Edge fillStyle0="0" fillStyle1="2" strokeStyle="1" edges="! 186 211[ 186 162 149 129"/>
                                                  <Edge fillStyle0="0" fillStyle1="2" strokeStyle="1" edges="! 168 270[ 186 242 186 211"/>
                                                  <Edge fillStyle0="0" fillStyle1="2" strokeStyle="1" edges="! 149 129[ 117 99 81 99| 57 103[ 49 103 42 129[ 35 154 35 182"/>
                                                  <Edge fillStyle0="0" fillStyle1="0" strokeStyle="1" edges="! 129 218[ 140 218 144 203| 146 186[ 146 156 130 166[ 113 175 115 197[ 117 218 129 218"/>
                                                  <Edge fillStyle0="1" fillStyle1="2" strokeStyle="1" edges="! 1 52| 324 173"/>
                                             </edges>
                                        </DOMShape>
                                   </elements>
                              </DOMFrame>
                         </frames>
                    </DOMLayer>
                    <DOMLayer name="Layer 2">
                         <frames>
                              <DOMFrame index="0" motionTweenScale="false" keyMode="8192">
                                   <elements>
                                        <DOMShape isFloating="true">
                                             <fills>
                                                  <FillStyle index="1">
                                                       <SolidColor color="#cccccc" alpha="1.0"/>
                                                  </FillStyle>
                                             </fills>
                                             <strokes/>
                                             <edges>
                                                  <Edge fillStyle0="0" fillStyle1="1" strokeStyle="0" edges="! 207 223| 207 224| 203 241| 207 223"/>
                                                  <Edge fillStyle0="0" fillStyle1="1" strokeStyle="0" edges="! 33 128| 34 129| 33 130| 33 128"/>
                                             </edges>
                                        </DOMShape>
                                   </elements>
                              </DOMFrame>
                         </frames>
                    </DOMLayer>
               </layers>
          </DOMTimeline>
     </timeline>
</DOMSymbolItem>
